Metadata-Version: 2.1
Name: feditools
Version: 0.1.0a5
Summary: Python tools for the Fediverse.
Home-page: https://github.com/soundbytesoftware/feditools
Author: Nigel Small
Author-email: technige@nige.tech
License: MIT
Platform: UNKNOWN
Classifier: Development Status :: 3 - Alpha
Classifier: Intended Audience :: Developers
Classifier: License :: OSI Approved :: MIT License
Classifier: Programming Language :: Python :: 3
Classifier: Programming Language :: Python :: 3.7
Classifier: Programming Language :: Python :: 3.8
Classifier: Programming Language :: Python :: 3.9
Classifier: Programming Language :: Python :: 3.10
Classifier: Programming Language :: Python :: 3 :: Only
Requires-Python: >=3.7, <4
License-File: LICENSE.md
